techfin/__init__.py
techfin-0.0.1.dist-info/LICENCE.txt
techfin-0.0.1.dist-info/METADATA
techfin-0.0.1.dist-info/WHEEL
techfin-0.0.1.dist-info/top_level.txt
techfin-0.0.1.dist-info/RECORD
