Metadata-Version: 2.1
Name: techfin
Version: 0.0.1
Summary: techfin : A package for technical analysis
Home-page: https://github.com/ut-upwards/techfin
Author: UTKARSH SAHAYA
Author-email: sahai.utkarsh@gmail.com
Keywords: techical-analysis,finance,tech_fin,indicators,RSI,MACD,MFI,Moving Average
Classifier: Development Status :: 4 - Beta
Classifier: Intended Audience :: Developers
Classifier: Programming Language :: Python :: 3
Classifier: License :: OSI Approved :: MIT License
Classifier: Operating System :: OS Independent
License-File: LICENCE.txt
Requires-Dist: pandas
Requires-Dist: numpy
Requires-Dist: matplotlib
Requires-Dist: yfinance
